pyaspeller/__init__.py
pyaspeller/errors.py
pyaspeller/speller.py
pyaspeller/word.py
pyaspeller/yandex_speller.py
pyaspeller-2.0.1.dist-info/METADATA
pyaspeller-2.0.1.dist-info/WHEEL
pyaspeller-2.0.1.dist-info/entry_points.txt
pyaspeller-2.0.1.dist-info/licenses/LICENSE
pyaspeller-2.0.1.dist-info/RECORD
