Metadata-Version: 2.4
Name: pyaspeller
Version: 2.0.1
Summary: Search tool typos in the text, files and websites.
Project-URL: homepage, https://github.com/oriontvv/pyaspeller
Project-URL: repository, https://github.com/oriontvv/pyaspeller
Project-URL: changelog, https://github.com/oriontvv/pyaspeller/blob/master/CHANGELOG.md
Author-email: Vasiliy Taranov <taranov.vv@gmail.com>
Maintainer-email: Vasiliy Taranov <taranov.vv@gmail.com>
License: Apache License
License-File: LICENSE
Keywords: api,spell,spellcheck,spelling,text,yandex
Classifier: Development Status :: 5 - Production/Stable
Classifier: Intended Audience :: Developers
Classifier: Intended Audience :: End Users/Desktop
Classifier: License :: OSI Approved :: Apache Software License
Classifier: Operating System :: OS Independent
Classifier: Programming Language :: Python :: 3
Classifier: Topic :: Text Processing :: Linguistic
Requires-Python: >=3.9
Requires-Dist: requests>=2.32.3
